README.rst
setup.py
imagemodal/__init__.py
imagemodal/models.py
imagemodal/settings.py
imagemodal/views.py
imagemodal/xblocks.py
imagemodal/mixins/__init__.py
imagemodal/mixins/fragment.py
imagemodal/mixins/scenario.py
imagemodal/public/draggabilly.pkgd.min.js
imagemodal/public/view.css
imagemodal/public/view.js
imagemodal/public/view.less
imagemodal/scenarios/image-modal-many.xml
imagemodal/scenarios/image-modal-single.xml
imagemodal/templates/view.html
imagemodal/translations/en/LC_MESSAGES/django.po
xblock_image_modal.egg-info/PKG-INFO
xblock_image_modal.egg-info/SOURCES.txt
xblock_image_modal.egg-info/dependency_links.txt
xblock_image_modal.egg-info/entry_points.txt
xblock_image_modal.egg-info/requires.txt
xblock_image_modal.egg-info/top_level.txt