Metadata-Version: 1.1
Name: xblock-image-modal
Version: 1.0.2
Summary: A full-screen image modal XBlock
Home-page: https://github.com/Stanford-Online/xblock-image-modal
Author: stv
Author-email: stv@stanford.edu
License: AGPL-3.0
Platform: UNKNOWN
Classifier: Intended Audience :: Developers
Classifier: Intended Audience :: Education
Classifier: License :: OSI Approved :: GNU Affero General Public License v3
Classifier: Operating System :: OS Independent
Classifier: Programming Language :: JavaScript
Classifier: Programming Language :: Python
Classifier: Topic :: Education
Classifier: Topic :: Internet :: WWW/HTTP
